deepinc/__init__.py
deepinc/backbone/MNISTMLP.py
deepinc/backbone/MNISTMLP_LWM.py
deepinc/backbone/MNISTMLP_PNN.py
deepinc/backbone/ResNet.py
deepinc/backbone/ResNet_LWM.py
deepinc/backbone/ResNet_PNN.py
deepinc/backbone/VAE.py
deepinc/backbone/VAE_MLP.py
deepinc/backbone/__init__.py
deepinc/backbone/utils/__init__.py
deepinc/backbone/utils/modules.py
deepinc/datasets/__init__.py
deepinc/datasets/seq_cifar10.py
deepinc/datasets/seq_cifar100.py
deepinc/datasets/seq_imagenet.py
deepinc/datasets/seq_mnist.py
deepinc/datasets/seq_tinyimagenet.py
deepinc/datasets/transforms/__init__.py
deepinc/datasets/transforms/denormalization.py
deepinc/datasets/transforms/permutation.py
deepinc/datasets/transforms/rotation.py
deepinc/datasets/utils/__init__.py
deepinc/datasets/utils/incremental_dataset.py
deepinc/datasets/utils/validation.py
deepinc/models/__init__.py
deepinc/models/clser.py
deepinc/models/deepinversion.py
deepinc/models/der.py
deepinc/models/derpp.py
deepinc/models/dgr.py
deepinc/models/discoil.py
deepinc/models/gem.py
deepinc/models/gpm.py
deepinc/models/gss.py
deepinc/models/hal.py
deepinc/models/joint.py
deepinc/models/lwf.py
deepinc/models/lwm.py
deepinc/models/oewc.py
deepinc/models/pass.py
deepinc/models/pnn.py
deepinc/models/si.py
deepinc/models/utils/__init__.py
deepinc/models/utils/incremental_model.py
deepinc/utils/__init__.py
deepinc/utils/args.py
deepinc/utils/buffer.py
deepinc/utils/conf.py
deepinc/utils/gss_buffer.py
deepinc/utils/metrics.py
deepinc/utils/ring_buffer.py
deepinc/utils/training.py
visintincremental/__init__.py
visintincremental/visintincremental.py
visintincremental/backbone/MNISTMLP.py
visintincremental/backbone/MNISTMLP_LWM.py
visintincremental/backbone/MNISTMLP_PNN.py
visintincremental/backbone/ResNet.py
visintincremental/backbone/ResNet_LWM.py
visintincremental/backbone/ResNet_PNN.py
visintincremental/backbone/VAE.py
visintincremental/backbone/VAE_MLP.py
visintincremental/backbone/__init__.py
deepinc-0.1.0.dist-info/AUTHORS.rst
deepinc-0.1.0.dist-info/LICENSE
deepinc-0.1.0.dist-info/METADATA
deepinc-0.1.0.dist-info/WHEEL
deepinc-0.1.0.dist-info/top_level.txt
deepinc-0.1.0.dist-info/RECORD
